stylelens_image
