Metadata-Version: 1.0
Name: stylelens-image
Version: 0.0.10
Summary: stylelens-image
Home-page: UNKNOWN
Author: UNKNOWN
Author-email: master@bluehack.net
License: UNKNOWN
Keywords: BlueLens,stylelens-image
Platform: UNKNOWN
